trayer/__init__.py
trayer/tray_icon.py
trayer-0.1.1.dist-info/licenses/LICENSE
trayer-0.1.1.dist-info/METADATA
trayer-0.1.1.dist-info/WHEEL
trayer-0.1.1.dist-info/top_level.txt
trayer-0.1.1.dist-info/RECORD
