Metadata-Version: 2.4
Name: trayer
Version: 0.1.1
Summary: System tray icons for GTK4 applications - betray GNOME 3's philosophy with style!
Author: enne2
License: MIT
Project-URL: Homepage, https://github.com/enne2/trayer
Project-URL: Repository, https://github.com/enne2/trayer
Project-URL: Bug Tracker, https://github.com/enne2/trayer/issues
Keywords: gtk4,tray,system-tray,statusnotifier,dbusmenu,gnome,linux
Classifier: Development Status :: 4 - Beta
Classifier: Intended Audience :: Developers
Classifier: License :: OSI Approved :: MIT License
Classifier: Programming Language :: Python :: 3
Classifier: Programming Language :: Python :: 3.8
Classifier: Programming Language :: Python :: 3.9
Classifier: Programming Language :: Python :: 3.10
Classifier: Programming Language :: Python :: 3.11
Classifier: Programming Language :: Python :: 3.12
Classifier: Topic :: Desktop Environment :: Gnome
Classifier: Topic :: Software Development :: Libraries :: Python Modules
Classifier: Topic :: System :: Monitoring
Classifier: Operating System :: POSIX :: Linux
Requires-Python: >=3.8
License-File: LICENSE
Requires-Dist: PyGObject>=3.42.0
Requires-Dist: dbus-python>=1.2.0
Dynamic: license-file
